pandasklar/__init__.py
pandasklar/__main__.py
pandasklar/aggregate.py
pandasklar/analyse.py
pandasklar/compare.py
pandasklar/config.py
pandasklar/content.py
pandasklar/develop.py
pandasklar/pandas.py
pandasklar/plot.py
pandasklar/rank.py
pandasklar/scale.py
pandasklar/string.py
pandasklar/subsets.py
pandasklar/type_info.py
pandasklar/values_info.py
pandasklar-0.3.6.dist-info/LICENSE
pandasklar-0.3.6.dist-info/METADATA
pandasklar-0.3.6.dist-info/WHEEL
pandasklar-0.3.6.dist-info/entry_points.txt
pandasklar-0.3.6.dist-info/top_level.txt
pandasklar-0.3.6.dist-info/RECORD
