Metadata-Version: 2.1
Name: pandasklar
Version: 0.3.6
Summary: Toolbox / Ecosystem for data science. Easier handling of pandas, especially when thinking in SQL.
Author-email: djekra <hopsalla@gmail.com>
License: MIT
Project-URL: Homepage, https://github.com/djekra/pandasklar
Classifier: Programming Language :: Python :: 3
Classifier: License :: OSI Approved :: MIT License
Classifier: Operating System :: OS Independent
Requires-Python: >=3.8
License-File: LICENSE
Requires-Dist: pandas
Requires-Dist: numpy
Requires-Dist: perlin-noise
Requires-Dist: termcolor
Requires-Dist: bpyth
Requires-Dist: blab
